firamir.py
firamir-1.0.0.dist-info/WHEEL
firamir-1.0.0.dist-info/METADATA
firamir-1.0.0.dist-info/RECORD
